search_in_syspath/LICENSE
search_in_syspath/README.MD
search_in_syspath/__init__.py
search_in_syspath/requirements.txt
search_in_syspath/thirdparty.json
search_in_syspath-0.10.dist-info/LICENSE.rst
search_in_syspath-0.10.dist-info/METADATA
search_in_syspath-0.10.dist-info/WHEEL
search_in_syspath-0.10.dist-info/top_level.txt
search_in_syspath-0.10.dist-info/RECORD
